lark_grammars/__init__.py
lark_grammars/grammars.py
lark_grammars/grammars/bc.lark
lark_grammars/grammars/gedcom.lark
lark_grammars/grammars/lua.lark
lark_grammars/grammars/mime.lark
lark_grammars/grammars/palindrome.lark
lark_grammars/grammars/pf.lark
lark_grammars/grammars/phone_number.lark
lark_grammars/grammars/postal.lark
lark_grammars/grammars/regex.lark
lark_grammars/grammars/restructuredtext.lark
lark_grammars/grammars/rfc_1738.lark
lark_grammars/grammars/rfc_2396.lark
lark_grammars/grammars/rfc_2397.lark
lark_grammars/grammars/rfc_5321.lark
lark_grammars/grammars/rfc_5545.lark
lark_grammars/grammars/rfc_6531.lark
lark_grammars/grammars/rfc_822.lark
lark_grammars/grammars/rfc_822_datetime.lark
lark_grammars/grammars/robotstxt.lark
lark_grammars/grammars/sqlite.lark
lark_grammars/grammars/subunit_v1.lark
lark_grammars/grammars/tap13.lark
lark_grammars/grammars/toml.lark
lark_grammars/grammars/yaml.lark
lark_grammars-0.3.0.dist-info/LICENSE
lark_grammars-0.3.0.dist-info/METADATA
lark_grammars-0.3.0.dist-info/WHEEL
lark_grammars-0.3.0.dist-info/top_level.txt
lark_grammars-0.3.0.dist-info/RECORD
