Metadata-Version: 2.1
Name: lark-grammars
Version: 0.3.0
Summary: Lark grammars for using wht Hypothesis testing library
Home-page: https://github.com/ligurio/lark-grammars
Author: Sergey Bronnikov
Author-email: estetus@gmail.com
License: UNKNOWN
Project-URL: Bug Reports, https://github.com/ligurio/lark-grammars/issues
Project-URL: Source, https://github.com/ligurio/lark-grammars
Platform: UNKNOWN
Classifier: Operating System :: OS Independent
Classifier: Programming Language :: Python :: 3
Classifier: Topic :: Software Development :: Testing
Requires-Python: >=3.6
Requires-Dist: hypothesis
Requires-Dist: lark-parser
